[
    {"id":"1","gestionMateria":"Cuero Nobuck","idUnidadBase":"1","precioBase":"400","idTipoMateria":"1","estado":"1"},
    {"id":"2","gestionMateria":"Puntera termoadherible","idUnidadBase":"5","precioBase":"4000","idTipoMateria":"2","estado":"1"},
    {"id":"3","gestionMateria":"Forro badana","idUnidadBase":"1","precioBase":"300","idTipoMateria":"2","estado":"1"},
    {"id":"4","gestionMateria":"Suela caucho antideslizante","idUnidadBase":"5","precioBase":"10000","idTipoMateria":"2","estado":"1"},
    {"id":"5","gestionMateria":"Odena vulcan # 1.5","idUnidadBase":"1","precioBase":"57","idTipoMateria":"2","estado":"1"},
    {"id":"6","gestionMateria":"Hilo 69 x 500M","idUnidadBase":"2","precioBase":"18","idTipoMateria":"4","estado":"1"},
    {"id":"7","gestionMateria":"Hilo 46 x 500M","idUnidadBase":"2","precioBase":"17","idTipoMateria":"4","estado":"1"},
    {"id":"8","gestionMateria":"Marquilla","idUnidadBase":"4","precioBase":"5","idTipoMateria":"3","estado":"1"},
    {"id":"9","gestionMateria":"Ojalete # 8","idUnidadBase":"4","precioBase":"5","idTipoMateria":"3","estado":"1"},
    {"id":"10","gestionMateria":"Neopreno x 2000 ml","idUnidadBase":"6","precioBase":"4","idTipoMateria":"4","estado":"1"},
    {"id":"11","gestionMateria":"Solucion de caucho x 2000 ml","idUnidadBase":"6","precioBase":"3","idTipoMateria":"4","estado":"1"},
    {"id":"12","gestionMateria":"Pegante pvc x 5000 ml","idUnidadBase":"6","precioBase":"11","idTipoMateria":"4","estado":"1"},
    {"id":"13","gestionMateria":"Halogenante x 1000 ml","idUnidadBase":"6","precioBase":"18","idTipoMateria":"4","estado":"1"},
    {"id":"14","gestionMateria":"Cambrion acerado","idUnidadBase":"5","precioBase":"800","idTipoMateria":"4","estado":"1"},
    {"id":"15","gestionMateria":"Cordones","idUnidadBase":"5","precioBase":"500","idTipoMateria":"4","estado":"1"},
    {"id":"16","gestionMateria":"Plantilla","idUnidadBase":"5","precioBase":"500","idTipoMateria":"4","estado":"1"},
    {"id":"17","gestionMateria":"Forro textil","idUnidadBase":"2","precioBase":"8800","idTipoMateria":"1","estado":"1"},
    {"id":"18","gestionMateria":"Cordonera doble","idUnidadBase":"4","precioBase":"40","idTipoMateria":"3","estado":"1"},
    {"id":"19","gestionMateria":"Reata","idUnidadBase":"2","precioBase":"150","idTipoMateria":"1","estado":"1"},
    {"id":"20","gestionMateria":"Malla Alicante","idUnidadBase":"2","precioBase":"14000","idTipoMateria":"1","estado":"1"},
    {"id":"21","gestionMateria":"Pegante amarillo","idUnidadBase":"6","precioBase":"125000","idTipoMateria":"2","estado":"1"},
    {"id":"22","gestionMateria":"Pimpon","idUnidadBase":"3","precioBase":"4800","idTipoMateria":"1","estado":"1"},
    {"id":"23","gestionMateria":"Produeva","idUnidadBase":"2","precioBase":"7200","idTipoMateria":"1","estado":"1"},
    {"id":"24","gestionMateria":"Aplique sintético","idUnidadBase":"2","precioBase":"16000","idTipoMateria":"1","estado":"1"},
    {"id":"25","gestionMateria":"Registro","idUnidadBase":"5","precioBase":"50","idTipoMateria":"1","estado":"1"},
    {"id":"26","gestionMateria":"Caja taco","idUnidadBase":"4","precioBase":"1000","idTipoMateria":"1","estado":"1"},
    {"id":"27","gestionMateria":"Corte sintético","idUnidadBase":"5","precioBase":"1670","idTipoMateria":"1","estado":"1"},
    {"id":"28","gestionMateria":"Forro sintético","idUnidadBase":"5","precioBase":"650","idTipoMateria":"1","estado":"1"},
    {"id":"29","gestionMateria":"Puntera","idUnidadBase":"5","precioBase":"60","idTipoMateria":"2","estado":"1"},
    {"id":"30","gestionMateria":"Contrafuerte","idUnidadBase":"5","precioBase":"70","idTipoMateria":"2","estado":"1"},
    {"id":"31","gestionMateria":"Suela en expanso","idUnidadBase":"5","precioBase":"4850","idTipoMateria":"1","estado":"1"},
    {"id":"32","gestionMateria":"Hiladillo","idUnidadBase":"5","precioBase":"50","idTipoMateria":"2","estado":"1"},
    {"id":"33","gestionMateria":"Puntera de emplantillado","idUnidadBase":"5","precioBase":"150","idTipoMateria":"2","estado":"1"},
    {"id":"34","gestionMateria":"Pegante látex","idUnidadBase":"6","precioBase":"270","idTipoMateria":"1","estado":"1"},
    {"id":"35","gestionMateria":"Solución de caucho","idUnidadBase":"6","precioBase":"180","idTipoMateria":"1","estado":"1"},
    {"id":"36","gestionMateria":"Bolsa","idUnidadBase":"4","precioBase":"25","idTipoMateria":"2","estado":"1"}
]
